CHANGES.rst
LICENSE
MANIFEST.in
README.rst
setup.py
minefield/__init__.py
minefield/gminefield.py
minefield/mlogging.py
minefield.egg-info/PKG-INFO
minefield.egg-info/SOURCES.txt
minefield.egg-info/dependency_links.txt
minefield.egg-info/entry_points.txt
minefield.egg-info/top_level.txt
minefield/server/atomic.h
minefield/server/buffer.c
minefield/server/buffer.h
minefield/server/client.c
minefield/server/client.h
minefield/server/heapq.c
minefield/server/heapq.h
minefield/server/http_parser.c
minefield/server/http_parser.h
minefield/server/http_request_parser.c
minefield/server/http_request_parser.h
minefield/server/input.c
minefield/server/input.h
minefield/server/log.c
minefield/server/log.h
minefield/server/minefield.h
minefield/server/picoev.h
minefield/server/picoev_epoll.c
minefield/server/picoev_kqueue.c
minefield/server/picoev_select.c
minefield/server/request.c
minefield/server/request.h
minefield/server/response.c
minefield/server/response.h
minefield/server/server.c
minefield/server/server.h
minefield/server/time_cache.c
minefield/server/time_cache.h
minefield/server/timer.c
minefield/server/timer.h
minefield/server/util.c
minefield/server/util.h